vercel_cli/vendor/LICENSE
vercel_cli/vendor/README.md
vercel_cli/vendor/package.json
vercel_cli/vendor/dist/VERCEL_DIR_README.txt
vercel_cli/vendor/dist/builder-worker.cjs
vercel_cli/vendor/dist/get-latest-worker.cjs
vercel_cli/vendor/dist/index.js
vercel_cli/vendor/dist/vc.js
vercel_cli/vendor/node_modules/.package-lock.json
vercel_cli/vendor/node_modules/@vercel/build-utils/CHANGELOG.md
vercel_cli/vendor/node_modules/@vercel/build-utils/LICENSE
vercel_cli/vendor/node_modules/@vercel/build-utils/build.mjs
vercel_cli/vendor/node_modules/@vercel/build-utils/file-blob.js
vercel_cli/vendor/node_modules/@vercel/build-utils/file-fs-ref.js
vercel_cli/vendor/node_modules/@vercel/build-utils/file-ref.js
vercel_cli/vendor/node_modules/@vercel/build-utils/lambda.js
vercel_cli/vendor/node_modules/@vercel/build-utils/package.json
vercel_cli/vendor/node_modules/@vercel/build-utils/dist/clone-env.d.ts
vercel_cli/vendor/node_modules/@vercel/build-utils/dist/clone-env.js
vercel_cli/vendor/node_modules/@vercel/build-utils/dist/debug.d.ts
vercel_cli/vendor/node_modules/@vercel/build-utils/dist/debug.js
vercel_cli/vendor/node_modules/@vercel/build-utils/dist/default-cache-path-glob.d.ts
vercel_cli/vendor/node_modules/@vercel/build-utils/dist/default-cache-path-glob.js
vercel_cli/vendor/node_modules/@vercel/build-utils/dist/edge-function.d.ts
vercel_cli/vendor/node_modules/@vercel/build-utils/dist/edge-function.js
vercel_cli/vendor/node_modules/@vercel/build-utils/dist/errors.d.ts
vercel_cli/vendor/node_modules/@vercel/build-utils/dist/errors.js
vercel_cli/vendor/node_modules/@vercel/build-utils/dist/file-blob.d.ts
vercel_cli/vendor/node_modules/@vercel/build-utils/dist/file-blob.js
vercel_cli/vendor/node_modules/@vercel/build-utils/dist/file-fs-ref.d.ts
vercel_cli/vendor/node_modules/@vercel/build-utils/dist/file-fs-ref.js
vercel_cli/vendor/node_modules/@vercel/build-utils/dist/file-ref.d.ts
vercel_cli/vendor/node_modules/@vercel/build-utils/dist/file-ref.js
vercel_cli-50.9.6.dist-info/METADATA
vercel_cli-50.9.6.dist-info/WHEEL
vercel_cli-50.9.6.dist-info/entry_points.txt
vercel_cli-50.9.6.dist-info/RECORD
