Metadata-Version: 2.4
Name: vercel-cli
Version: 50.9.6
Summary: Vercel CLI packaged for Python (bundled Node.js, vendored npm)
Project-URL: Homepage, https://github.com/nuage-studio/vercel-cli-python
Project-URL: Repository, https://github.com/nuage-studio/vercel-cli-python
Project-URL: Issues, https://github.com/nuage-studio/vercel-cli-python/issues
Project-URL: Documentation, https://github.com/nuage-studio/vercel-cli-python#readme
Author: Nuage
Maintainer: Nuage
Keywords: cli,deployment,edge,functions,nodejs,npm,serverless,vercel,wrapper
Classifier: Development Status :: 5 - Production/Stable
Classifier: Environment :: Console
Classifier: Intended Audience :: Developers
Classifier: Operating System :: OS Independent
Classifier: Programming Language :: Python :: 3
Classifier: Programming Language :: Python :: 3 :: Only
Classifier: Programming Language :: Python :: 3.8
Classifier: Programming Language :: Python :: 3.9
Classifier: Programming Language :: Python :: 3.10
Classifier: Programming Language :: Python :: 3.11
Classifier: Programming Language :: Python :: 3.12
Classifier: Programming Language :: Python :: 3.13
Classifier: Topic :: Software Development :: Build Tools
Classifier: Topic :: System :: Systems Administration
Classifier: Topic :: Utilities
Requires-Python: >=3.8
Requires-Dist: nodejs-wheel-binaries==22.16.0
